usbid/__init__.py
usbid/fs.py
usbid/tests.py
usbid/testing/1.tgz
usbid/testing/2.tgz
usbid/testing/3.tgz
usbid-2.2.dist-info/LICENSE.rst
usbid-2.2.dist-info/METADATA
usbid-2.2.dist-info/WHEEL
usbid-2.2.dist-info/top_level.txt
usbid-2.2.dist-info/zip-safe
usbid-2.2.dist-info/RECORD
