Metadata-Version: 2.1
Name: usbid
Version: 2.2
Summary: USB file system API for Linux
Home-page: http://pypi.python.org/pypi/usbid
Author: BlueDynamics Alliance
Author-email: dev@bluedynamics.com
License: Simplified BSD
Keywords: usb python
Classifier: Operating System :: POSIX :: Linux
Classifier: Programming Language :: Python
Classifier: Topic :: Software Development
Classifier: License :: OSI Approved :: BSD License
Classifier: Programming Language :: Python
Classifier: Programming Language :: Python :: 3.7
Classifier: Programming Language :: Python :: 3.8
Classifier: Programming Language :: Python :: 3.9
Classifier: Programming Language :: Python :: 3.10
Classifier: Programming Language :: Python :: 3.11
License-File: LICENSE.rst
Requires-Dist: setuptools
Provides-Extra: test
Requires-Dist: coverage ; extra == 'test'
